Metadata-Version: 2.1
Name: otp-generator
Version: 0.1.0
Summary: A Python tool to generate and verify One Time Password (OTP)
Home-page: https://gitlab.com/frier17/otp_generator.git
Author: https://gitlab.com/frier17/
Author-email: frier17@a17s.co.uk
License: MIT
Platform: UNKNOWN
Classifier: Development Status :: 3 - Alpha
Classifier: Intended Audience :: Developers
Classifier: Topic :: Security :: Cryptography
Classifier: License :: OSI Approved :: MIT License
Classifier: Programming Language :: Python :: 3
Classifier: Programming Language :: Python :: 3.8
